{
	"id": "secretmanager_v1beta2_secretmanagerservice_secret_create",
	"title": "create secret",
	"description": "Secret Manager sample showing how to create_secret",
	"collection": "secretmanager_api_samples",
	"products": [
		"secretmanager"
	],
	"type": "rpc",
	"rpcMetadata": {
		"api": "secretmanager.googleapis.com",
		"method": "create_secret"
	},
	"regionTags": [
		{
			"name": "secretmanager_v1beta2_secretmanagerservice_secret_create"
		}
	],
	"variant": [
		{
			"name": "python",
			"created": "2025-06-09",
			"generatedBy": "sample-assistance v0.0.0"
		}
	]
}